django_next_auth_adapter/__init__.py
django_next_auth_adapter/admin.py
django_next_auth_adapter/apps.py
django_next_auth_adapter/mixins.py
django_next_auth_adapter/models.py
django_next_auth_adapter/permissions.py
django_next_auth_adapter/response.py
django_next_auth_adapter/serializers.py
django_next_auth_adapter/settings.py
django_next_auth_adapter/signals.py
django_next_auth_adapter/tests.py
django_next_auth_adapter/urls.py
django_next_auth_adapter/views.py
django_next_auth_adapter-0.0.4.dist-info/AUTHORS.md
django_next_auth_adapter-0.0.4.dist-info/METADATA
django_next_auth_adapter-0.0.4.dist-info/WHEEL
django_next_auth_adapter-0.0.4.dist-info/top_level.txt
django_next_auth_adapter-0.0.4.dist-info/RECORD
