Metadata-Version: 2.1
Name: django-next-auth-adapter
Version: 0.0.4
Summary: A Django app to to handle server side requirests of next-auth-http-adapter
Home-page: https://github.com/mabdullahadeel/django-next-auth-adapter
Author: Abdullah Adeel
Author-email: contact.abdadeel@gamil.com
License: MIT license
Keywords: django_next_auth_adapter,django,next-auth,auth,rest,restframework
Classifier: Development Status :: 2 - Pre-Alpha
Classifier: Intended Audience :: Developers
Classifier: License :: OSI Approved :: MIT License
Classifier: Natural Language :: English
Classifier: Programming Language :: Python :: 3
Classifier: Programming Language :: Python :: 3.6
Classifier: Programming Language :: Python :: 3.7
Classifier: Programming Language :: Python :: 3.8
Classifier: Programming Language :: Python :: 3.9
Classifier: Framework :: Django
Classifier: Framework :: Django :: 2.0
Classifier: Framework :: Django :: 2.1
Classifier: Framework :: Django :: 2.2
Classifier: Framework :: Django :: 3.0
Classifier: Framework :: Django :: 3.1
Classifier: Framework :: Django :: 3.2
Classifier: Framework :: Django :: 4.0
Requires-Python: >=3.7
License-File: AUTHORS.md
Requires-Dist: Django >=3.0.0
Requires-Dist: djangorestframework >=3.0
